MIP/LICENSE
MIP/__init__.py
MIP/geom/__init__.py
MIP/geom/another_parser.py
MIP/geom/cells.py
MIP/geom/composition.py
MIP/geom/copt.py
MIP/geom/forcad.py
MIP/geom/grammars/__init__.py
MIP/geom/grammars/geom.ebnf
MIP/geom/grammars/multioperand.py
MIP/geom/main.py
MIP/geom/parsegeom.py
MIP/geom/semantics.py
MIP/geom/surfaces.py
MIP/geom/testgrammar.py
MIP/geom/transforms.py
MIP/mip/__init__.py
MIP/mip/blocks.py
MIP/mip/cards.py
MIP/mip/cellcard.py
MIP/mip/datacard.py
MIP/mip/main.py
MIP/mip/readme.rst
MIP/mip/surfacecard.py
MIP/mip/utils.py
MIP/tests.py
t4_geom_convert/Kernel/BoundaryCondition/CBoundCond.py
t4_geom_convert/Kernel/BoundaryCondition/CConversionBoundaryCondition.py
t4_geom_convert/Kernel/BoundaryCondition/__init__.py
t4_geom_convert/Kernel/Composition/Abundances.py
t4_geom_convert/Kernel/Composition/CCompositionMCNP.py
t4_geom_convert/Kernel/Composition/CCompositionT4.py
t4_geom_convert/Kernel/Composition/CDictCompositionMCNP.py
t4_geom_convert/Kernel/Composition/CompositionConversionMCNPToT4.py
t4_geom_convert/Kernel/Composition/ConstructCompositionT4.py
t4_geom_convert/Kernel/Composition/ConvertIsotope.py
t4_geom_convert/Kernel/Composition/EIsotopeAtomicNumberMCNP.py
t4_geom_convert/Kernel/Composition/EIsotopeNameElementT4.py
t4_geom_convert/Kernel/Composition/__init__.py
t4_geom_convert/Kernel/Configuration/__init__.py
t4_geom_convert/Kernel/Exceptions/__init__.py
t4_geom_convert/Kernel/FileHandlers/Parser/ParseMCNPCell.py
t4_geom_convert/Kernel/FileHandlers/Parser/ParseMCNPComposition.py
t4_geom_convert/Kernel/FileHandlers/Parser/ParseMCNPSurface.py
t4_geom_convert/Kernel/FileHandlers/Parser/__init__.py
t4_geom_convert/Kernel/FileHandlers/Writer/WriteT4BoundCond.py
t4_geom_convert/Kernel/FileHandlers/Writer/WriteT4Composition.py
t4_geom_convert/Kernel/FileHandlers/Writer/WriteT4GeomComp.py
t4_geom_convert/Kernel/FileHandlers/Writer/WriteT4Geometry.py
t4_geom_convert/Kernel/FileHandlers/Writer/__init__.py
t4_geom_convert-1.1.3.dist-info/COPYING
t4_geom_convert-1.1.3.dist-info/METADATA
t4_geom_convert-1.1.3.dist-info/WHEEL
t4_geom_convert-1.1.3.dist-info/entry_points.txt
t4_geom_convert-1.1.3.dist-info/RECORD
