Metadata-Version: 2.1
Name: t4_geom_convert
Version: 1.1.3
Summary: A tool to convert MCNP geometries into the TRIPOLI-4 format
Home-page: https://www.cea.fr/energies/tripoli-4/tripoli-4/pre_post_tools/t4_geom_convert/
License: GPL-3.0-or-later
Author: Davide Mancusi
Author-email: davide.mancusi@cea.fr
Maintainer: Davide Mancusi
Maintainer-email: davide.mancusi@cea.fr
Requires-Python: >=3.8,<4
Classifier: Development Status :: 4 - Beta
Classifier: Environment :: Console
Classifier: License :: OSI Approved :: GNU General Public License v3 or later (GPLv3+)
Classifier: Operating System :: POSIX :: Linux
Classifier: Programming Language :: Python :: 3
Classifier: Programming Language :: Python :: 3.8
Classifier: Programming Language :: Python :: 3.9
Classifier: Programming Language :: Python :: 3.10
Classifier: Programming Language :: Python :: 3.11
Classifier: Programming Language :: Python :: 3.12
Classifier: Programming Language :: Python :: 3.13
Classifier: Topic :: Scientific/Engineering :: Physics
Requires-Dist: importlib-metadata (>=4.4,<5.0)
Requires-Dist: numpy (>=1.24,<2.0)
Requires-Dist: tatsu (>=5.6,<6.0)
Project-URL: Bug tracker, https://github.com/arekfu/t4_geom_convert/issues/
Project-URL: Documentation, https://t4-geom-convert.readthedocs.io/
Project-URL: Repository, https://github.com/arekfu/t4_geom_convert/
